pysetwindowpos/__init__.py
pysetwindowpos/setwindowpos.py
pysetwindowpos/util.py
pysetwindowpos-0.1.0.dist-info/LICENSE
pysetwindowpos-0.1.0.dist-info/METADATA
pysetwindowpos-0.1.0.dist-info/WHEEL
pysetwindowpos-0.1.0.dist-info/top_level.txt
pysetwindowpos-0.1.0.dist-info/RECORD
