Metadata-Version: 2.1
Name: pysetwindowpos
Version: 0.1.0
Summary: Python wrapper for setwindowpos.
Author-email: Marc Stober <marcstober@gmail.com>
License: MIT License        
Project-URL: Homepage, https://github.com/marcstober/pysetwindowpos
Project-URL: Bug Tracker, https://github.com/marcstober/pysetwindowpos/issues
Classifier: Programming Language :: Python :: 3
Classifier: License :: OSI Approved :: MIT License
Classifier: Operating System :: Microsoft :: Windows
Classifier: Development Status :: 3 - Alpha
Requires-Python: >=3.3
License-File: LICENSE
